elastic_transport/__init__.py
elastic_transport/_async_transport.py
elastic_transport/_compat.py
elastic_transport/_exceptions.py
elastic_transport/_models.py
elastic_transport/_node_pool.py
elastic_transport/_otel.py
elastic_transport/_response.py
elastic_transport/_serializer.py
elastic_transport/_transport.py
elastic_transport/_utils.py
elastic_transport/_version.py
elastic_transport/client_utils.py
elastic_transport/py.typed
elastic_transport/_node/__init__.py
elastic_transport/_node/_base.py
elastic_transport/_node/_base_async.py
elastic_transport/_node/_http_aiohttp.py
elastic_transport/_node/_http_httpx.py
elastic_transport/_node/_http_requests.py
elastic_transport/_node/_http_urllib3.py
elastic_transport/_node/_urllib3_chain_certs.py
elastic_transport-8.15.1.dist-info/LICENSE
elastic_transport-8.15.1.dist-info/METADATA
elastic_transport-8.15.1.dist-info/WHEEL
elastic_transport-8.15.1.dist-info/top_level.txt
elastic_transport-8.15.1.dist-info/RECORD
