Metadata-Version: 2.1
Name: elastic-transport
Version: 8.15.1
Summary: Transport classes and utilities shared among Python Elastic client libraries
Home-page: https://github.com/elastic/elastic-transport-python
Author: Elastic Client Library Maintainers
Author-email: client-libs@elastic.co
Project-URL: Source Code, https://github.com/elastic/elastic-transport-python
Project-URL: Issue Tracker, https://github.com/elastic/elastic-transport-python/issues
Project-URL: Documentation, https://elastic-transport-python.readthedocs.io
Classifier: Development Status :: 5 - Production/Stable
Classifier: License :: OSI Approved :: Apache Software License
Classifier: Intended Audience :: Developers
Classifier: Operating System :: OS Independent
Classifier: Programming Language :: Python
Classifier: Programming Language :: Python :: 3
Classifier: Programming Language :: Python :: 3.8
Classifier: Programming Language :: Python :: 3.9
Classifier: Programming Language :: Python :: 3.10
Classifier: Programming Language :: Python :: 3.11
Classifier: Programming Language :: Python :: 3.12
Classifier: Programming Language :: Python :: 3.13
Classifier: Programming Language :: Python :: Implementation :: CPython
Classifier: Programming Language :: Python :: Implementation :: PyPy
Requires-Python: >=3.8
License-File: LICENSE
Requires-Dist: urllib3<3,>=1.26.2
Requires-Dist: certifi
Requires-Dist: importlib-metadata; python_version < "3.8"
Provides-Extra: develop
Requires-Dist: pytest; extra == "develop"
Requires-Dist: pytest-cov; extra == "develop"
Requires-Dist: pytest-mock; extra == "develop"
Requires-Dist: pytest-asyncio; extra == "develop"
Requires-Dist: pytest-httpserver; extra == "develop"
Requires-Dist: trustme; extra == "develop"
Requires-Dist: requests; extra == "develop"
Requires-Dist: aiohttp; extra == "develop"
Requires-Dist: httpx; extra == "develop"
Requires-Dist: httpcore<1.0.6; extra == "develop"
Requires-Dist: respx; extra == "develop"
Requires-Dist: opentelemetry-api; extra == "develop"
Requires-Dist: opentelemetry-sdk; extra == "develop"
Requires-Dist: orjson; extra == "develop"
Requires-Dist: sphinx>2; extra == "develop"
Requires-Dist: furo; extra == "develop"
Requires-Dist: sphinx-autodoc-typehints; extra == "develop"
